{"entries": [
{ "teamSkillConditionId": "30010000", "teamSkillId": 10101001, "teamSkillMinPairsReq": 2, "u4": 40, "u5": 41, "u6": 0, "u7": 0, "u8": 0, "u9": 0, "u10": 0, "u11": 0 },
{ "teamSkillConditionId": "30010000", "teamSkillId": 10101002, "teamSkillMinPairsReq": 2, "u4": 0, "u5": 0, "u6": 0, "u7": 0, "u8": 0, "u9": 0, "u10": 0, "u11": 0 },
{ "teamSkillConditionId": "30010000", "teamSkillId": 10101003, "teamSkillMinPairsReq": 2, "u4": 40, "u5": 41, "u6": 0, "u7": 0, "u8": 0, "u9": 0, "u10": 0, "u11": 0 },
{ "teamSkillConditionId": "30010000", "teamSkillId": 10102001, "teamSkillMinPairsReq": 2, "u4": 40, "u5": 41, "u6": 0, "u7": 0, "u8": 0, "u9": 0, "u10": 0, "u11": 0 },
{ "teamSkillConditionId": "30010000", "teamSkillId": 10102002, "teamSkillMinPairsReq": 2, "u4": 0, "u5": 0, "u6": 0, "u7": 0, "u8": 0, "u9": 0, "u10": 0, "u11": 0 },
{ "teamSkillConditionId": "30010000", "teamSkillId": 10102003, "teamSkillMinPairsReq": 2, "u4": 40, "u5": 41, "u6": 0, "u7": 0, "u8": 0, "u9": 0, "u10": 0, "u11": 0 },
{ "teamSkillConditionId": "30010000", "teamSkillId": 10103001, "teamSkillMinPairsReq": 2, "u4": 40, "u5": 41, "u6": 0, "u7": 0, "u8": 0, "u9": 0, "u10": 0, "u11": 0 },
{ "teamSkillConditionId": "30010000", "teamSkillId": 10103002, "teamSkillMinPairsReq": 2, "u4": 0, "u5": 0, "u6": 0, "u7": 0, "u8": 0, "u9": 0, "u10": 0, "u11": 0 },
{ "teamSkillConditionId": "30010000", "teamSkillId": 10103003, "teamSkillMinPairsReq": 2, "u4": 40, "u5": 41, "u6": 0, "u7": 0, "u8": 0, "u9": 0, "u10": 0, "u11": 0 },
{ "teamSkillConditionId": "30010000", "teamSkillId": 10104001, "teamSkillMinPairsReq": 2, "u4": 40, "u5": 41, "u6": 0, "u7": 0, "u8": 0, "u9": 0, "u10": 0, "u11": 0 },
{ "teamSkillConditionId": "30010000", "teamSkillId": 10104002, "teamSkillMinPairsReq": 2, "u4": 0, "u5": 0, "u6": 0, "u7": 0, "u8": 0, "u9": 0, "u10": 0, "u11": 0 },
{ "teamSkillConditionId": "30010000", "teamSkillId": 10104003, "teamSkillMinPairsReq": 2, "u4": 40, "u5": 41, "u6": 0, "u7": 0, "u8": 0, "u9": 0, "u10": 0, "u11": 0 },
{ "teamSkillConditionId": "30010000", "teamSkillId": 10105001, "teamSkillMinPairsReq": 2, "u4": 40, "u5": 41, "u6": 0, "u7": 0, "u8": 0, "u9": 0, "u10": 0, "u11": 0 },
{ "teamSkillConditionId": "30010000", "teamSkillId": 10105002, "teamSkillMinPairsReq": 2, "u4": 0, "u5": 0, "u6": 0, "u7": 0, "u8": 0, "u9": 0, "u10": 0, "u11": 0 },
{ "teamSkillConditionId": "30010000", "teamSkillId": 10105003, "teamSkillMinPairsReq": 2, "u4": 40, "u5": 41, "u6": 0, "u7": 0, "u8": 0, "u9": 0, "u10": 0, "u11": 0 },
{ "teamSkillConditionId": "30010000", "teamSkillId": 10106001, "teamSkillMinPairsReq": 2, "u4": 40, "u5": 41, "u6": 0, "u7": 0, "u8": 0, "u9": 0, "u10": 0, "u11": 0 },
{ "teamSkillConditionId": "30010000", "teamSkillId": 10106002, "teamSkillMinPairsReq": 2, "u4": 0, "u5": 0, "u6": 0, "u7": 0, "u8": 0, "u9": 0, "u10": 0, "u11": 0 },
{ "teamSkillConditionId": "30010000", "teamSkillId": 10106003, "teamSkillMinPairsReq": 2, "u4": 40, "u5": 41, "u6": 0, "u7": 0, "u8": 0, "u9": 0, "u10": 0, "u11": 0 },
{ "teamSkillConditionId": "30010000", "teamSkillId": 10107001, "teamSkillMinPairsReq": 2, "u4": 40, "u5": 41, "u6": 0, "u7": 0, "u8": 0, "u9": 0, "u10": 0, "u11": 0 },
{ "teamSkillConditionId": "30010000", "teamSkillId": 10107002, "teamSkillMinPairsReq": 2, "u4": 0, "u5": 0, "u6": 0, "u7": 0, "u8": 0, "u9": 0, "u10": 0, "u11": 0 },
{ "teamSkillConditionId": "30010000", "teamSkillId": 10107003, "teamSkillMinPairsReq": 2, "u4": 40, "u5": 41, "u6": 0, "u7": 0, "u8": 0, "u9": 0, "u10": 0, "u11": 0 },
{ "teamSkillConditionId": "30010000", "teamSkillId": 10108001, "teamSkillMinPairsReq": 2, "u4": 40, "u5": 41, "u6": 0, "u7": 0, "u8": 0, "u9": 0, "u10": 0, "u11": 0 },
{ "teamSkillConditionId": "30010000", "teamSkillId": 10108002, "teamSkillMinPairsReq": 2, "u4": 0, "u5": 0, "u6": 0, "u7": 0, "u8": 0, "u9": 0, "u10": 0, "u11": 0 },
{ "teamSkillConditionId": "30010000", "teamSkillId": 10108003, "teamSkillMinPairsReq": 2, "u4": 40, "u5": 41, "u6": 0, "u7": 0, "u8": 0, "u9": 0, "u10": 0, "u11": 0 },
{ "teamSkillConditionId": "30010000", "teamSkillId": 10109001, "teamSkillMinPairsReq": 2, "u4": 40, "u5": 41, "u6": 0, "u7": 0, "u8": 0, "u9": 0, "u10": 0, "u11": 0 },
{ "teamSkillConditionId": "30010000", "teamSkillId": 10109002, "teamSkillMinPairsReq": 2, "u4": 0, "u5": 0, "u6": 0, "u7": 0, "u8": 0, "u9": 0, "u10": 0, "u11": 0 },
{ "teamSkillConditionId": "30010000", "teamSkillId": 10109003, "teamSkillMinPairsReq": 2, "u4": 40, "u5": 41, "u6": 0, "u7": 0, "u8": 0, "u9": 0, "u10": 0, "u11": 0 },
{ "teamSkillConditionId": "30010000", "teamSkillId": 10110001, "teamSkillMinPairsReq": 2, "u4": 40, "u5": 41, "u6": 0, "u7": 0, "u8": 0, "u9": 0, "u10": 0, "u11": 0 },
{ "teamSkillConditionId": "30010000", "teamSkillId": 10110002, "teamSkillMinPairsReq": 2, "u4": 0, "u5": 0, "u6": 0, "u7": 0, "u8": 0, "u9": 0, "u10": 0, "u11": 0 },
{ "teamSkillConditionId": "30010000", "teamSkillId": 10110003, "teamSkillMinPairsReq": 2, "u4": 40, "u5": 41, "u6": 0, "u7": 0, "u8": 0, "u9": 0, "u10": 0, "u11": 0 },
{ "teamSkillConditionId": "30010000", "teamSkillId": 10111001, "teamSkillMinPairsReq": 2, "u4": 40, "u5": 41, "u6": 0, "u7": 0, "u8": 0, "u9": 0, "u10": 0, "u11": 0 },
{ "teamSkillConditionId": "30010000", "teamSkillId": 10111002, "teamSkillMinPairsReq": 2, "u4": 0, "u5": 0, "u6": 0, "u7": 0, "u8": 0, "u9": 0, "u10": 0, "u11": 0 },
{ "teamSkillConditionId": "30010000", "teamSkillId": 10111003, "teamSkillMinPairsReq": 2, "u4": 40, "u5": 41, "u6": 0, "u7": 0, "u8": 0, "u9": 0, "u10": 0, "u11": 0 },
{ "teamSkillConditionId": "30010000", "teamSkillId": 10112001, "teamSkillMinPairsReq": 2, "u4": 40, "u5": 41, "u6": 0, "u7": 0, "u8": 0, "u9": 0, "u10": 0, "u11": 0 },
{ "teamSkillConditionId": "30010000", "teamSkillId": 10112002, "teamSkillMinPairsReq": 2, "u4": 0, "u5": 0, "u6": 0, "u7": 0, "u8": 0, "u9": 0, "u10": 0, "u11": 0 },
{ "teamSkillConditionId": "30010000", "teamSkillId": 10112003, "teamSkillMinPairsReq": 2, "u4": 40, "u5": 41, "u6": 0, "u7": 0, "u8": 0, "u9": 0, "u10": 0, "u11": 0 },
{ "teamSkillConditionId": "30010000", "teamSkillId": 10113001, "teamSkillMinPairsReq": 2, "u4": 40, "u5": 41, "u6": 0, "u7": 0, "u8": 0, "u9": 0, "u10": 0, "u11": 0 },
{ "teamSkillConditionId": "30010000", "teamSkillId": 10113002, "teamSkillMinPairsReq": 2, "u4": 0, "u5": 0, "u6": 0, "u7": 0, "u8": 0, "u9": 0, "u10": 0, "u11": 0 },
{ "teamSkillConditionId": "30010000", "teamSkillId": 10113003, "teamSkillMinPairsReq": 2, "u4": 40, "u5": 41, "u6": 0, "u7": 0, "u8": 0, "u9": 0, "u10": 0, "u11": 0 },
{ "teamSkillConditionId": "30010000", "teamSkillId": 10114001, "teamSkillMinPairsReq": 2, "u4": 40, "u5": 41, "u6": 0, "u7": 0, "u8": 0, "u9": 0, "u10": 0, "u11": 0 },
{ "teamSkillConditionId": "30010000", "teamSkillId": 10114002, "teamSkillMinPairsReq": 2, "u4": 0, "u5": 0, "u6": 0, "u7": 0, "u8": 0, "u9": 0, "u10": 0, "u11": 0 },
{ "teamSkillConditionId": "30010000", "teamSkillId": 10114003, "teamSkillMinPairsReq": 2, "u4": 40, "u5": 41, "u6": 0, "u7": 0, "u8": 0, "u9": 0, "u10": 0, "u11": 0 },
{ "teamSkillConditionId": "30010000", "teamSkillId": 10115001, "teamSkillMinPairsReq": 2, "u4": 40, "u5": 41, "u6": 0, "u7": 0, "u8": 0, "u9": 0, "u10": 0, "u11": 0 },
{ "teamSkillConditionId": "30010000", "teamSkillId": 10115002, "teamSkillMinPairsReq": 2, "u4": 0, "u5": 0, "u6": 0, "u7": 0, "u8": 0, "u9": 0, "u10": 0, "u11": 0 },
{ "teamSkillConditionId": "30010000", "teamSkillId": 10115003, "teamSkillMinPairsReq": 2, "u4": 40, "u5": 41, "u6": 0, "u7": 0, "u8": 0, "u9": 0, "u10": 0, "u11": 0 },
{ "teamSkillConditionId": "30010000", "teamSkillId": 10116001, "teamSkillMinPairsReq": 2, "u4": 40, "u5": 41, "u6": 0, "u7": 0, "u8": 0, "u9": 0, "u10": 0, "u11": 0 },
{ "teamSkillConditionId": "30010000", "teamSkillId": 10116002, "teamSkillMinPairsReq": 2, "u4": 0, "u5": 0, "u6": 0, "u7": 0, "u8": 0, "u9": 0, "u10": 0, "u11": 0 },
{ "teamSkillConditionId": "30010000", "teamSkillId": 10116003, "teamSkillMinPairsReq": 2, "u4": 40, "u5": 41, "u6": 0, "u7": 0, "u8": 0, "u9": 0, "u10": 0, "u11": 0 },
{ "teamSkillConditionId": "30010000", "teamSkillId": 10117001, "teamSkillMinPairsReq": 2, "u4": 40, "u5": 41, "u6": 0, "u7": 0, "u8": 0, "u9": 0, "u10": 0, "u11": 0 },
{ "teamSkillConditionId": "30010000", "teamSkillId": 10117002, "teamSkillMinPairsReq": 2, "u4": 0, "u5": 0, "u6": 0, "u7": 0, "u8": 0, "u9": 0, "u10": 0, "u11": 0 },
{ "teamSkillConditionId": "30010000", "teamSkillId": 10117003, "teamSkillMinPairsReq": 2, "u4": 40, "u5": 41, "u6": 0, "u7": 0, "u8": 0, "u9": 0, "u10": 0, "u11": 0 },
{ "teamSkillConditionId": "30010000", "teamSkillId": 10118001, "teamSkillMinPairsReq": 2, "u4": 40, "u5": 41, "u6": 0, "u7": 0, "u8": 0, "u9": 0, "u10": 0, "u11": 0 },
{ "teamSkillConditionId": "30010000", "teamSkillId": 10118002, "teamSkillMinPairsReq": 2, "u4": 0, "u5": 0, "u6": 0, "u7": 0, "u8": 0, "u9": 0, "u10": 0, "u11": 0 },
{ "teamSkillConditionId": "30010000", "teamSkillId": 10118003, "teamSkillMinPairsReq": 2, "u4": 40, "u5": 41, "u6": 0, "u7": 0, "u8": 0, "u9": 0, "u10": 0, "u11": 0 },
{ "teamSkillConditionId": "30020000", "teamSkillId": 10201001, "teamSkillMinPairsReq": 2, "u4": 40, "u5": 41, "u6": 0, "u7": 0, "u8": 0, "u9": 0, "u10": 0, "u11": 0 },
{ "teamSkillConditionId": "30020000", "teamSkillId": 10201002, "teamSkillMinPairsReq": 2, "u4": 0, "u5": 0, "u6": 0, "u7": 0, "u8": 0, "u9": 0, "u10": 0, "u11": 0 },
{ "teamSkillConditionId": "30020000", "teamSkillId": 10201003, "teamSkillMinPairsReq": 2, "u4": 40, "u5": 41, "u6": 0, "u7": 0, "u8": 0, "u9": 0, "u10": 0, "u11": 0 },
{ "teamSkillConditionId": "30020000", "teamSkillId": 10202001, "teamSkillMinPairsReq": 2, "u4": 40, "u5": 41, "u6": 0, "u7": 0, "u8": 0, "u9": 0, "u10": 0, "u11": 0 },
{ "teamSkillConditionId": "30020000", "teamSkillId": 10202002, "teamSkillMinPairsReq": 2, "u4": 0, "u5": 0, "u6": 0, "u7": 0, "u8": 0, "u9": 0, "u10": 0, "u11": 0 },
{ "teamSkillConditionId": "30020000", "teamSkillId": 10202003, "teamSkillMinPairsReq": 2, "u4": 40, "u5": 41, "u6": 0, "u7": 0, "u8": 0, "u9": 0, "u10": 0, "u11": 0 },
{ "teamSkillConditionId": "30020000", "teamSkillId": 10203001, "teamSkillMinPairsReq": 2, "u4": 40, "u5": 41, "u6": 0, "u7": 0, "u8": 0, "u9": 0, "u10": 0, "u11": 0 },
{ "teamSkillConditionId": "30020000", "teamSkillId": 10203002, "teamSkillMinPairsReq": 2, "u4": 0, "u5": 0, "u6": 0, "u7": 0, "u8": 0, "u9": 0, "u10": 0, "u11": 0 },
{ "teamSkillConditionId": "30020000", "teamSkillId": 10203003, "teamSkillMinPairsReq": 2, "u4": 40, "u5": 41, "u6": 0, "u7": 0, "u8": 0, "u9": 0, "u10": 0, "u11": 0 },
{ "teamSkillConditionId": "30020000", "teamSkillId": 10204001, "teamSkillMinPairsReq": 2, "u4": 40, "u5": 41, "u6": 0, "u7": 0, "u8": 0, "u9": 0, "u10": 0, "u11": 0 },
{ "teamSkillConditionId": "30020000", "teamSkillId": 10204002, "teamSkillMinPairsReq": 2, "u4": 0, "u5": 0, "u6": 0, "u7": 0, "u8": 0, "u9": 0, "u10": 0, "u11": 0 },
{ "teamSkillConditionId": "30020000", "teamSkillId": 10204003, "teamSkillMinPairsReq": 2, "u4": 40, "u5": 41, "u6": 0, "u7": 0, "u8": 0, "u9": 0, "u10": 0, "u11": 0 },
{ "teamSkillConditionId": "30020000", "teamSkillId": 10205001, "teamSkillMinPairsReq": 2, "u4": 40, "u5": 41, "u6": 0, "u7": 0, "u8": 0, "u9": 0, "u10": 0, "u11": 0 },
{ "teamSkillConditionId": "30020000", "teamSkillId": 10205002, "teamSkillMinPairsReq": 2, "u4": 0, "u5": 0, "u6": 0, "u7": 0, "u8": 0, "u9": 0, "u10": 0, "u11": 0 },
{ "teamSkillConditionId": "30020000", "teamSkillId": 10205003, "teamSkillMinPairsReq": 2, "u4": 40, "u5": 41, "u6": 0, "u7": 0, "u8": 0, "u9": 0, "u10": 0, "u11": 0 },
{ "teamSkillConditionId": "30020000", "teamSkillId": 10206001, "teamSkillMinPairsReq": 2, "u4": 40, "u5": 41, "u6": 0, "u7": 0, "u8": 0, "u9": 0, "u10": 0, "u11": 0 },
{ "teamSkillConditionId": "30020000", "teamSkillId": 10206002, "teamSkillMinPairsReq": 2, "u4": 0, "u5": 0, "u6": 0, "u7": 0, "u8": 0, "u9": 0, "u10": 0, "u11": 0 },
{ "teamSkillConditionId": "30020000", "teamSkillId": 10206003, "teamSkillMinPairsReq": 2, "u4": 40, "u5": 41, "u6": 0, "u7": 0, "u8": 0, "u9": 0, "u10": 0, "u11": 0 },
{ "teamSkillConditionId": "30020000", "teamSkillId": 10207001, "teamSkillMinPairsReq": 2, "u4": 40, "u5": 41, "u6": 0, "u7": 0, "u8": 0, "u9": 0, "u10": 0, "u11": 0 },
{ "teamSkillConditionId": "30020000", "teamSkillId": 10207002, "teamSkillMinPairsReq": 2, "u4": 0, "u5": 0, "u6": 0, "u7": 0, "u8": 0, "u9": 0, "u10": 0, "u11": 0 },
{ "teamSkillConditionId": "30020000", "teamSkillId": 10207003, "teamSkillMinPairsReq": 2, "u4": 40, "u5": 41, "u6": 0, "u7": 0, "u8": 0, "u9": 0, "u10": 0, "u11": 0 },
{ "teamSkillConditionId": "30020000", "teamSkillId": 10208001, "teamSkillMinPairsReq": 2, "u4": 40, "u5": 41, "u6": 0, "u7": 0, "u8": 0, "u9": 0, "u10": 0, "u11": 0 },
{ "teamSkillConditionId": "30020000", "teamSkillId": 10208002, "teamSkillMinPairsReq": 2, "u4": 0, "u5": 0, "u6": 0, "u7": 0, "u8": 0, "u9": 0, "u10": 0, "u11": 0 },
{ "teamSkillConditionId": "30020000", "teamSkillId": 10208003, "teamSkillMinPairsReq": 2, "u4": 40, "u5": 41, "u6": 0, "u7": 0, "u8": 0, "u9": 0, "u10": 0, "u11": 0 },
{ "teamSkillConditionId": "30020000", "teamSkillId": 10301001, "teamSkillMinPairsReq": 2, "u4": 40, "u5": 41, "u6": 0, "u7": 0, "u8": 0, "u9": 0, "u10": 0, "u11": 0 },
{ "teamSkillConditionId": "30020000", "teamSkillId": 10301002, "teamSkillMinPairsReq": 2, "u4": 0, "u5": 0, "u6": 0, "u7": 0, "u8": 0, "u9": 0, "u10": 0, "u11": 0 },
{ "teamSkillConditionId": "30020000", "teamSkillId": 10301003, "teamSkillMinPairsReq": 2, "u4": 40, "u5": 41, "u6": 0, "u7": 0, "u8": 0, "u9": 0, "u10": 0, "u11": 0 },
{ "teamSkillConditionId": "30020000", "teamSkillId": 10303001, "teamSkillMinPairsReq": 2, "u4": 40, "u5": 41, "u6": 0, "u7": 0, "u8": 0, "u9": 0, "u10": 0, "u11": 0 },
{ "teamSkillConditionId": "30020000", "teamSkillId": 10303002, "teamSkillMinPairsReq": 2, "u4": 0, "u5": 0, "u6": 0, "u7": 0, "u8": 0, "u9": 0, "u10": 0, "u11": 0 },
{ "teamSkillConditionId": "30020000", "teamSkillId": 10303003, "teamSkillMinPairsReq": 2, "u4": 40, "u5": 41, "u6": 0, "u7": 0, "u8": 0, "u9": 0, "u10": 0, "u11": 0 },
{ "teamSkillConditionId": "30020000", "teamSkillId": 10304001, "teamSkillMinPairsReq": 2, "u4": 40, "u5": 41, "u6": 0, "u7": 0, "u8": 0, "u9": 0, "u10": 0, "u11": 0 },
{ "teamSkillConditionId": "30020000", "teamSkillId": 10304002, "teamSkillMinPairsReq": 2, "u4": 0, "u5": 0, "u6": 0, "u7": 0, "u8": 0, "u9": 0, "u10": 0, "u11": 0 },
{ "teamSkillConditionId": "30020000", "teamSkillId": 10304003, "teamSkillMinPairsReq": 2, "u4": 40, "u5": 41, "u6": 0, "u7": 0, "u8": 0, "u9": 0, "u10": 0, "u11": 0 },
{ "teamSkillConditionId": "30020000", "teamSkillId": 10306001, "teamSkillMinPairsReq": 2, "u4": 40, "u5": 41, "u6": 0, "u7": 0, "u8": 0, "u9": 0, "u10": 0, "u11": 0 },
{ "teamSkillConditionId": "30020000", "teamSkillId": 10306002, "teamSkillMinPairsReq": 2, "u4": 0, "u5": 0, "u6": 0, "u7": 0, "u8": 0, "u9": 0, "u10": 0, "u11": 0 },
{ "teamSkillConditionId": "30020000", "teamSkillId": 10306003, "teamSkillMinPairsReq": 2, "u4": 40, "u5": 41, "u6": 0, "u7": 0, "u8": 0, "u9": 0, "u10": 0, "u11": 0 },
{ "teamSkillConditionId": "30020000", "teamSkillId": 10310001, "teamSkillMinPairsReq": 2, "u4": 40, "u5": 41, "u6": 0, "u7": 0, "u8": 0, "u9": 0, "u10": 0, "u11": 0 },
{ "teamSkillConditionId": "30020000", "teamSkillId": 10310003, "teamSkillMinPairsReq": 2, "u4": 40, "u5": 41, "u6": 0, "u7": 0, "u8": 0, "u9": 0, "u10": 0, "u11": 0 },
{ "teamSkillConditionId": "30020000", "teamSkillId": 10311001, "teamSkillMinPairsReq": 2, "u4": 40, "u5": 41, "u6": 0, "u7": 0, "u8": 0, "u9": 0, "u10": 0, "u11": 0 },
{ "teamSkillConditionId": "30020000", "teamSkillId": 10311003, "teamSkillMinPairsReq": 2, "u4": 40, "u5": 41, "u6": 0, "u7": 0, "u8": 0, "u9": 0, "u10": 0, "u11": 0 },
{ "teamSkillConditionId": "30020000", "teamSkillId": 10312001, "teamSkillMinPairsReq": 2, "u4": 40, "u5": 41, "u6": 0, "u7": 0, "u8": 0, "u9": 0, "u10": 0, "u11": 0 },
{ "teamSkillConditionId": "30020000", "teamSkillId": 10312002, "teamSkillMinPairsReq": 2, "u4": 0, "u5": 0, "u6": 0, "u7": 0, "u8": 0, "u9": 0, "u10": 0, "u11": 0 },
{ "teamSkillConditionId": "30020000", "teamSkillId": 10312003, "teamSkillMinPairsReq": 2, "u4": 40, "u5": 41, "u6": 0, "u7": 0, "u8": 0, "u9": 0, "u10": 0, "u11": 0 },
{ "teamSkillConditionId": "30020000", "teamSkillId": 10315001, "teamSkillMinPairsReq": 2, "u4": 40, "u5": 41, "u6": 0, "u7": 0, "u8": 0, "u9": 0, "u10": 0, "u11": 0 },
{ "teamSkillConditionId": "30020000", "teamSkillId": 10315002, "teamSkillMinPairsReq": 2, "u4": 0, "u5": 0, "u6": 0, "u7": 0, "u8": 0, "u9": 0, "u10": 0, "u11": 0 },
{ "teamSkillConditionId": "30020000", "teamSkillId": 10315003, "teamSkillMinPairsReq": 2, "u4": 40, "u5": 41, "u6": 0, "u7": 0, "u8": 0, "u9": 0, "u10": 0, "u11": 0 },
{ "teamSkillConditionId": "30020000", "teamSkillId": 10316001, "teamSkillMinPairsReq": 2, "u4": 40, "u5": 41, "u6": 0, "u7": 0, "u8": 0, "u9": 0, "u10": 0, "u11": 0 },
{ "teamSkillConditionId": "30020000", "teamSkillId": 10316002, "teamSkillMinPairsReq": 2, "u4": 0, "u5": 0, "u6": 0, "u7": 0, "u8": 0, "u9": 0, "u10": 0, "u11": 0 },
{ "teamSkillConditionId": "30020000", "teamSkillId": 10316003, "teamSkillMinPairsReq": 2, "u4": 40, "u5": 41, "u6": 0, "u7": 0, "u8": 0, "u9": 0, "u10": 0, "u11": 0 },
{ "teamSkillConditionId": "30020000", "teamSkillId": 10401001, "teamSkillMinPairsReq": 2, "u4": 40, "u5": 41, "u6": 0, "u7": 0, "u8": 0, "u9": 0, "u10": 0, "u11": 0 },
{ "teamSkillConditionId": "30020000", "teamSkillId": 10401002, "teamSkillMinPairsReq": 2, "u4": 0, "u5": 0, "u6": 0, "u7": 0, "u8": 0, "u9": 0, "u10": 0, "u11": 0 },
{ "teamSkillConditionId": "30020000", "teamSkillId": 10401003, "teamSkillMinPairsReq": 2, "u4": 40, "u5": 41, "u6": 0, "u7": 0, "u8": 0, "u9": 0, "u10": 0, "u11": 0 },
{ "teamSkillConditionId": "30020000", "teamSkillId": 10402001, "teamSkillMinPairsReq": 2, "u4": 40, "u5": 41, "u6": 0, "u7": 0, "u8": 0, "u9": 0, "u10": 0, "u11": 0 },
{ "teamSkillConditionId": "30020000", "teamSkillId": 10402002, "teamSkillMinPairsReq": 2, "u4": 0, "u5": 0, "u6": 0, "u7": 0, "u8": 0, "u9": 0, "u10": 0, "u11": 0 },
{ "teamSkillConditionId": "30020000", "teamSkillId": 10402003, "teamSkillMinPairsReq": 2, "u4": 40, "u5": 41, "u6": 0, "u7": 0, "u8": 0, "u9": 0, "u10": 0, "u11": 0 },
{ "teamSkillConditionId": "30020000", "teamSkillId": 10403001, "teamSkillMinPairsReq": 2, "u4": 40, "u5": 41, "u6": 0, "u7": 0, "u8": 0, "u9": 0, "u10": 0, "u11": 0 },
{ "teamSkillConditionId": "30020000", "teamSkillId": 10403003, "teamSkillMinPairsReq": 2, "u4": 40, "u5": 41, "u6": 0, "u7": 0, "u8": 0, "u9": 0, "u10": 0, "u11": 0 },
{ "teamSkillConditionId": "30020000", "teamSkillId": 10404003, "teamSkillMinPairsReq": 2, "u4": 40, "u5": 41, "u6": 0, "u7": 0, "u8": 0, "u9": 0, "u10": 0, "u11": 0 },
{ "teamSkillConditionId": "30020000", "teamSkillId": 10406001, "teamSkillMinPairsReq": 2, "u4": 40, "u5": 41, "u6": 0, "u7": 0, "u8": 0, "u9": 0, "u10": 0, "u11": 0 },
{ "teamSkillConditionId": "30020000", "teamSkillId": 10406002, "teamSkillMinPairsReq": 2, "u4": 0, "u5": 0, "u6": 0, "u7": 0, "u8": 0, "u9": 0, "u10": 0, "u11": 0 },
{ "teamSkillConditionId": "30020000", "teamSkillId": 10406003, "teamSkillMinPairsReq": 2, "u4": 40, "u5": 41, "u6": 0, "u7": 0, "u8": 0, "u9": 0, "u10": 0, "u11": 0 },
{ "teamSkillConditionId": "30020000", "teamSkillId": 10407001, "teamSkillMinPairsReq": 2, "u4": 40, "u5": 41, "u6": 0, "u7": 0, "u8": 0, "u9": 0, "u10": 0, "u11": 0 },
{ "teamSkillConditionId": "30020000", "teamSkillId": 10407002, "teamSkillMinPairsReq": 2, "u4": 0, "u5": 0, "u6": 0, "u7": 0, "u8": 0, "u9": 0, "u10": 0, "u11": 0 },
{ "teamSkillConditionId": "30020000", "teamSkillId": 10407003, "teamSkillMinPairsReq": 2, "u4": 40, "u5": 41, "u6": 0, "u7": 0, "u8": 0, "u9": 0, "u10": 0, "u11": 0 },
{ "teamSkillConditionId": "30020000", "teamSkillId": 10411001, "teamSkillMinPairsReq": 2, "u4": 40, "u5": 41, "u6": 0, "u7": 0, "u8": 0, "u9": 0, "u10": 0, "u11": 0 },
{ "teamSkillConditionId": "30020000", "teamSkillId": 10411002, "teamSkillMinPairsReq": 2, "u4": 0, "u5": 0, "u6": 0, "u7": 0, "u8": 0, "u9": 0, "u10": 0, "u11": 0 },
{ "teamSkillConditionId": "30020000", "teamSkillId": 10411003, "teamSkillMinPairsReq": 2, "u4": 40, "u5": 41, "u6": 0, "u7": 0, "u8": 0, "u9": 0, "u10": 0, "u11": 0 },
{ "teamSkillConditionId": "30020000", "teamSkillId": 10412001, "teamSkillMinPairsReq": 2, "u4": 40, "u5": 41, "u6": 0, "u7": 0, "u8": 0, "u9": 0, "u10": 0, "u11": 0 },
{ "teamSkillConditionId": "30020000", "teamSkillId": 10412002, "teamSkillMinPairsReq": 2, "u4": 0, "u5": 0, "u6": 0, "u7": 0, "u8": 0, "u9": 0, "u10": 0, "u11": 0 },
{ "teamSkillConditionId": "30020000", "teamSkillId": 10412003, "teamSkillMinPairsReq": 2, "u4": 40, "u5": 41, "u6": 0, "u7": 0, "u8": 0, "u9": 0, "u10": 0, "u11": 0 },
{ "teamSkillConditionId": "30020000", "teamSkillId": 10413001, "teamSkillMinPairsReq": 2, "u4": 40, "u5": 41, "u6": 0, "u7": 0, "u8": 0, "u9": 0, "u10": 0, "u11": 0 },
{ "teamSkillConditionId": "30020000", "teamSkillId": 10413002, "teamSkillMinPairsReq": 2, "u4": 0, "u5": 0, "u6": 0, "u7": 0, "u8": 0, "u9": 0, "u10": 0, "u11": 0 },
{ "teamSkillConditionId": "30020000", "teamSkillId": 10413003, "teamSkillMinPairsReq": 2, "u4": 40, "u5": 41, "u6": 0, "u7": 0, "u8": 0, "u9": 0, "u10": 0, "u11": 0 },
{ "teamSkillConditionId": "30020000", "teamSkillId": 19905001, "teamSkillMinPairsReq": 2, "u4": 40, "u5": 41, "u6": 0, "u7": 0, "u8": 0, "u9": 0, "u10": 0, "u11": 0 },
{ "teamSkillConditionId": "30020000", "teamSkillId": 19905002, "teamSkillMinPairsReq": 2, "u4": 0, "u5": 0, "u6": 0, "u7": 0, "u8": 0, "u9": 0, "u10": 0, "u11": 0 },
{ "teamSkillConditionId": "30020000", "teamSkillId": 19905003, "teamSkillMinPairsReq": 2, "u4": 40, "u5": 41, "u6": 0, "u7": 0, "u8": 0, "u9": 0, "u10": 0, "u11": 0 },
{ "teamSkillConditionId": "30020000", "teamSkillId": 19910001, "teamSkillMinPairsReq": 2, "u4": 40, "u5": 41, "u6": 0, "u7": 0, "u8": 0, "u9": 0, "u10": 0, "u11": 0 },
{ "teamSkillConditionId": "30020000", "teamSkillId": 19910002, "teamSkillMinPairsReq": 2, "u4": 0, "u5": 0, "u6": 0, "u7": 0, "u8": 0, "u9": 0, "u10": 0, "u11": 0 },
{ "teamSkillConditionId": "30020000", "teamSkillId": 19910003, "teamSkillMinPairsReq": 2, "u4": 40, "u5": 41, "u6": 0, "u7": 0, "u8": 0, "u9": 0, "u10": 0, "u11": 0 },
{ "teamSkillConditionId": "30020000", "teamSkillId": 19915001, "teamSkillMinPairsReq": 2, "u4": 40, "u5": 41, "u6": 0, "u7": 0, "u8": 0, "u9": 0, "u10": 0, "u11": 0 },
{ "teamSkillConditionId": "30020000", "teamSkillId": 19915002, "teamSkillMinPairsReq": 2, "u4": 0, "u5": 0, "u6": 0, "u7": 0, "u8": 0, "u9": 0, "u10": 0, "u11": 0 },
{ "teamSkillConditionId": "30020000", "teamSkillId": 19915003, "teamSkillMinPairsReq": 2, "u4": 40, "u5": 41, "u6": 0, "u7": 0, "u8": 0, "u9": 0, "u10": 0, "u11": 0 },
{ "teamSkillConditionId": "30020000", "teamSkillId": 19916001, "teamSkillMinPairsReq": 2, "u4": 40, "u5": 41, "u6": 0, "u7": 0, "u8": 0, "u9": 0, "u10": 0, "u11": 0 },
{ "teamSkillConditionId": "30020000", "teamSkillId": 19916002, "teamSkillMinPairsReq": 2, "u4": 0, "u5": 0, "u6": 0, "u7": 0, "u8": 0, "u9": 0, "u10": 0, "u11": 0 },
{ "teamSkillConditionId": "30020000", "teamSkillId": 19916003, "teamSkillMinPairsReq": 2, "u4": 40, "u5": 41, "u6": 0, "u7": 0, "u8": 0, "u9": 0, "u10": 0, "u11": 0 },
{ "teamSkillConditionId": "30020000", "teamSkillId": 19918001, "teamSkillMinPairsReq": 2, "u4": 40, "u5": 41, "u6": 0, "u7": 0, "u8": 0, "u9": 0, "u10": 0, "u11": 0 },
{ "teamSkillConditionId": "30020000", "teamSkillId": 19918002, "teamSkillMinPairsReq": 2, "u4": 0, "u5": 0, "u6": 0, "u7": 0, "u8": 0, "u9": 0, "u10": 0, "u11": 0 },
{ "teamSkillConditionId": "30020000", "teamSkillId": 19918003, "teamSkillMinPairsReq": 2, "u4": 40, "u5": 41, "u6": 0, "u7": 0, "u8": 0, "u9": 0, "u10": 0, "u11": 0 },
{ "teamSkillConditionId": "30020000", "teamSkillId": 19919001, "teamSkillMinPairsReq": 2, "u4": 40, "u5": 41, "u6": 0, "u7": 0, "u8": 0, "u9": 0, "u10": 0, "u11": 0 },
{ "teamSkillConditionId": "30020000", "teamSkillId": 19919002, "teamSkillMinPairsReq": 2, "u4": 0, "u5": 0, "u6": 0, "u7": 0, "u8": 0, "u9": 0, "u10": 0, "u11": 0 },
{ "teamSkillConditionId": "30020000", "teamSkillId": 19919003, "teamSkillMinPairsReq": 2, "u4": 40, "u5": 41, "u6": 0, "u7": 0, "u8": 0, "u9": 0, "u10": 0, "u11": 0 },
{ "teamSkillConditionId": "30020000", "teamSkillId": 19920001, "teamSkillMinPairsReq": 2, "u4": 40, "u5": 41, "u6": 0, "u7": 0, "u8": 0, "u9": 0, "u10": 0, "u11": 0 },
{ "teamSkillConditionId": "30020000", "teamSkillId": 19920002, "teamSkillMinPairsReq": 2, "u4": 0, "u5": 0, "u6": 0, "u7": 0, "u8": 0, "u9": 0, "u10": 0, "u11": 0 },
{ "teamSkillConditionId": "30020000", "teamSkillId": 19920003, "teamSkillMinPairsReq": 2, "u4": 40, "u5": 41, "u6": 0, "u7": 0, "u8": 0, "u9": 0, "u10": 0, "u11": 0 },
{ "teamSkillConditionId": "30020000", "teamSkillId": 19923001, "teamSkillMinPairsReq": 2, "u4": 40, "u5": 41, "u6": 0, "u7": 0, "u8": 0, "u9": 0, "u10": 0, "u11": 0 },
{ "teamSkillConditionId": "30020000", "teamSkillId": 19926001, "teamSkillMinPairsReq": 2, "u4": 40, "u5": 41, "u6": 0, "u7": 0, "u8": 0, "u9": 0, "u10": 0, "u11": 0 },
{ "teamSkillConditionId": "30020000", "teamSkillId": 19926002, "teamSkillMinPairsReq": 2, "u4": 0, "u5": 0, "u6": 0, "u7": 0, "u8": 0, "u9": 0, "u10": 0, "u11": 0 },
{ "teamSkillConditionId": "30020000", "teamSkillId": 19926003, "teamSkillMinPairsReq": 2, "u4": 40, "u5": 41, "u6": 0, "u7": 0, "u8": 0, "u9": 0, "u10": 0, "u11": 0 },
{ "teamSkillConditionId": "30020000", "teamSkillId": 19931003, "teamSkillMinPairsReq": 2, "u4": 40, "u5": 41, "u6": 0, "u7": 0, "u8": 0, "u9": 0, "u10": 0, "u11": 0 },
{ "teamSkillConditionId": "30020000", "teamSkillId": 19932001, "teamSkillMinPairsReq": 2, "u4": 40, "u5": 41, "u6": 0, "u7": 0, "u8": 0, "u9": 0, "u10": 0, "u11": 0 },
{ "teamSkillConditionId": "30020000", "teamSkillId": 19932002, "teamSkillMinPairsReq": 2, "u4": 0, "u5": 0, "u6": 0, "u7": 0, "u8": 0, "u9": 0, "u10": 0, "u11": 0 },
{ "teamSkillConditionId": "30020000", "teamSkillId": 19932003, "teamSkillMinPairsReq": 2, "u4": 40, "u5": 41, "u6": 0, "u7": 0, "u8": 0, "u9": 0, "u10": 0, "u11": 0 },
{ "teamSkillConditionId": "30020000", "teamSkillId": 19934001, "teamSkillMinPairsReq": 2, "u4": 40, "u5": 41, "u6": 0, "u7": 0, "u8": 0, "u9": 0, "u10": 0, "u11": 0 },
{ "teamSkillConditionId": "30020000", "teamSkillId": 19934002, "teamSkillMinPairsReq": 2, "u4": 0, "u5": 0, "u6": 0, "u7": 0, "u8": 0, "u9": 0, "u10": 0, "u11": 0 },
{ "teamSkillConditionId": "30020000", "teamSkillId": 19934003, "teamSkillMinPairsReq": 2, "u4": 40, "u5": 41, "u6": 0, "u7": 0, "u8": 0, "u9": 0, "u10": 0, "u11": 0 },
{ "teamSkillConditionId": "30020000", "teamSkillId": 19935001, "teamSkillMinPairsReq": 2, "u4": 40, "u5": 41, "u6": 0, "u7": 0, "u8": 0, "u9": 0, "u10": 0, "u11": 0 },
{ "teamSkillConditionId": "30020000", "teamSkillId": 19937001, "teamSkillMinPairsReq": 2, "u4": 40, "u5": 41, "u6": 0, "u7": 0, "u8": 0, "u9": 0, "u10": 0, "u11": 0 },
{ "teamSkillConditionId": "30020000", "teamSkillId": 19937002, "teamSkillMinPairsReq": 2, "u4": 0, "u5": 0, "u6": 0, "u7": 0, "u8": 0, "u9": 0, "u10": 0, "u11": 0 },
{ "teamSkillConditionId": "30020000", "teamSkillId": 19937003, "teamSkillMinPairsReq": 2, "u4": 40, "u5": 41, "u6": 0, "u7": 0, "u8": 0, "u9": 0, "u10": 0, "u11": 0 },
{ "teamSkillConditionId": "30020000", "teamSkillId": 19943001, "teamSkillMinPairsReq": 2, "u4": 40, "u5": 41, "u6": 0, "u7": 0, "u8": 0, "u9": 0, "u10": 0, "u11": 0 },
{ "teamSkillConditionId": "30020000", "teamSkillId": 19943003, "teamSkillMinPairsReq": 2, "u4": 40, "u5": 41, "u6": 0, "u7": 0, "u8": 0, "u9": 0, "u10": 0, "u11": 0 },
{ "teamSkillConditionId": "30020000", "teamSkillId": 19944003, "teamSkillMinPairsReq": 2, "u4": 40, "u5": 41, "u6": 0, "u7": 0, "u8": 0, "u9": 0, "u10": 0, "u11": 0 },
{ "teamSkillConditionId": "30020000", "teamSkillId": 19947001, "teamSkillMinPairsReq": 2, "u4": 40, "u5": 41, "u6": 0, "u7": 0, "u8": 0, "u9": 0, "u10": 0, "u11": 0 },
{ "teamSkillConditionId": "30020000", "teamSkillId": 19951001, "teamSkillMinPairsReq": 2, "u4": 40, "u5": 41, "u6": 0, "u7": 0, "u8": 0, "u9": 0, "u10": 0, "u11": 0 },
{ "teamSkillConditionId": "30020000", "teamSkillId": 19951002, "teamSkillMinPairsReq": 2, "u4": 0, "u5": 0, "u6": 0, "u7": 0, "u8": 0, "u9": 0, "u10": 0, "u11": 0 },
{ "teamSkillConditionId": "30020000", "teamSkillId": 19951003, "teamSkillMinPairsReq": 2, "u4": 40, "u5": 41, "u6": 0, "u7": 0, "u8": 0, "u9": 0, "u10": 0, "u11": 0 },
{ "teamSkillConditionId": "30020000", "teamSkillId": 19952001, "teamSkillMinPairsReq": 2, "u4": 40, "u5": 41, "u6": 0, "u7": 0, "u8": 0, "u9": 0, "u10": 0, "u11": 0 },
{ "teamSkillConditionId": "30020000", "teamSkillId": 19952002, "teamSkillMinPairsReq": 2, "u4": 0, "u5": 0, "u6": 0, "u7": 0, "u8": 0, "u9": 0, "u10": 0, "u11": 0 },
{ "teamSkillConditionId": "30020000", "teamSkillId": 19952003, "teamSkillMinPairsReq": 2, "u4": 40, "u5": 41, "u6": 0, "u7": 0, "u8": 0, "u9": 0, "u10": 0, "u11": 0 },
{ "teamSkillConditionId": "30020000", "teamSkillId": 19953003, "teamSkillMinPairsReq": 2, "u4": 40, "u5": 41, "u6": 0, "u7": 0, "u8": 0, "u9": 0, "u10": 0, "u11": 0 },
{ "teamSkillConditionId": "30020000", "teamSkillId": 19954001, "teamSkillMinPairsReq": 2, "u4": 40, "u5": 41, "u6": 0, "u7": 0, "u8": 0, "u9": 0, "u10": 0, "u11": 0 },
{ "teamSkillConditionId": "30020000", "teamSkillId": 19954002, "teamSkillMinPairsReq": 2, "u4": 0, "u5": 0, "u6": 0, "u7": 0, "u8": 0, "u9": 0, "u10": 0, "u11": 0 },
{ "teamSkillConditionId": "30020000", "teamSkillId": 19954003, "teamSkillMinPairsReq": 2, "u4": 40, "u5": 41, "u6": 0, "u7": 0, "u8": 0, "u9": 0, "u10": 0, "u11": 0 },
{ "teamSkillConditionId": "30020000", "teamSkillId": 19955001, "teamSkillMinPairsReq": 2, "u4": 40, "u5": 41, "u6": 0, "u7": 0, "u8": 0, "u9": 0, "u10": 0, "u11": 0 },
{ "teamSkillConditionId": "30020000", "teamSkillId": 19955003, "teamSkillMinPairsReq": 2, "u4": 40, "u5": 41, "u6": 0, "u7": 0, "u8": 0, "u9": 0, "u10": 0, "u11": 0 },
{ "teamSkillConditionId": "30020000", "teamSkillId": 19956001, "teamSkillMinPairsReq": 2, "u4": 40, "u5": 41, "u6": 0, "u7": 0, "u8": 0, "u9": 0, "u10": 0, "u11": 0 },
{ "teamSkillConditionId": "30020000", "teamSkillId": 19956002, "teamSkillMinPairsReq": 2, "u4": 0, "u5": 0, "u6": 0, "u7": 0, "u8": 0, "u9": 0, "u10": 0, "u11": 0 },
{ "teamSkillConditionId": "30020000", "teamSkillId": 19956003, "teamSkillMinPairsReq": 2, "u4": 40, "u5": 41, "u6": 0, "u7": 0, "u8": 0, "u9": 0, "u10": 0, "u11": 0 },
{ "teamSkillConditionId": "30020000", "teamSkillId": 19957001, "teamSkillMinPairsReq": 2, "u4": 40, "u5": 41, "u6": 0, "u7": 0, "u8": 0, "u9": 0, "u10": 0, "u11": 0 },
{ "teamSkillConditionId": "30020000", "teamSkillId": 19958001, "teamSkillMinPairsReq": 2, "u4": 40, "u5": 41, "u6": 0, "u7": 0, "u8": 0, "u9": 0, "u10": 0, "u11": 0 },
{ "teamSkillConditionId": "30020000", "teamSkillId": 19958002, "teamSkillMinPairsReq": 2, "u4": 0, "u5": 0, "u6": 0, "u7": 0, "u8": 0, "u9": 0, "u10": 0, "u11": 0 },
{ "teamSkillConditionId": "30020000", "teamSkillId": 19958003, "teamSkillMinPairsReq": 2, "u4": 40, "u5": 41, "u6": 0, "u7": 0, "u8": 0, "u9": 0, "u10": 0, "u11": 0 },
{ "teamSkillConditionId": "30020000", "teamSkillId": 19959001, "teamSkillMinPairsReq": 2, "u4": 40, "u5": 41, "u6": 0, "u7": 0, "u8": 0, "u9": 0, "u10": 0, "u11": 0 },
{ "teamSkillConditionId": "30020000", "teamSkillId": 19959002, "teamSkillMinPairsReq": 2, "u4": 0, "u5": 0, "u6": 0, "u7": 0, "u8": 0, "u9": 0, "u10": 0, "u11": 0 },
{ "teamSkillConditionId": "30020000", "teamSkillId": 19959003, "teamSkillMinPairsReq": 2, "u4": 40, "u5": 41, "u6": 0, "u7": 0, "u8": 0, "u9": 0, "u10": 0, "u11": 0 },
{ "teamSkillConditionId": "30020000", "teamSkillId": 19960001, "teamSkillMinPairsReq": 2, "u4": 40, "u5": 41, "u6": 0, "u7": 0, "u8": 0, "u9": 0, "u10": 0, "u11": 0 },
{ "teamSkillConditionId": "30020000", "teamSkillId": 19960002, "teamSkillMinPairsReq": 2, "u4": 0, "u5": 0, "u6": 0, "u7": 0, "u8": 0, "u9": 0, "u10": 0, "u11": 0 },
{ "teamSkillConditionId": "30020000", "teamSkillId": 19960003, "teamSkillMinPairsReq": 2, "u4": 40, "u5": 41, "u6": 0, "u7": 0, "u8": 0, "u9": 0, "u10": 0, "u11": 0 },
{ "teamSkillConditionId": "30020000", "teamSkillId": 19961001, "teamSkillMinPairsReq": 2, "u4": 40, "u5": 41, "u6": 0, "u7": 0, "u8": 0, "u9": 0, "u10": 0, "u11": 0 },
{ "teamSkillConditionId": "30020000", "teamSkillId": 19961003, "teamSkillMinPairsReq": 2, "u4": 40, "u5": 41, "u6": 0, "u7": 0, "u8": 0, "u9": 0, "u10": 0, "u11": 0 },
{ "teamSkillConditionId": "30020000", "teamSkillId": 19962001, "teamSkillMinPairsReq": 2, "u4": 40, "u5": 41, "u6": 0, "u7": 0, "u8": 0, "u9": 0, "u10": 0, "u11": 0 },
{ "teamSkillConditionId": "30020000", "teamSkillId": 19962002, "teamSkillMinPairsReq": 2, "u4": 0, "u5": 0, "u6": 0, "u7": 0, "u8": 0, "u9": 0, "u10": 0, "u11": 0 },
{ "teamSkillConditionId": "30020000", "teamSkillId": 19962003, "teamSkillMinPairsReq": 2, "u4": 40, "u5": 41, "u6": 0, "u7": 0, "u8": 0, "u9": 0, "u10": 0, "u11": 0 },
{ "teamSkillConditionId": "30020000", "teamSkillId": 19963001, "teamSkillMinPairsReq": 2, "u4": 40, "u5": 41, "u6": 0, "u7": 0, "u8": 0, "u9": 0, "u10": 0, "u11": 0 },
{ "teamSkillConditionId": "30020000", "teamSkillId": 19964001, "teamSkillMinPairsReq": 2, "u4": 40, "u5": 41, "u6": 0, "u7": 0, "u8": 0, "u9": 0, "u10": 0, "u11": 0 },
{ "teamSkillConditionId": "30020000", "teamSkillId": 19964002, "teamSkillMinPairsReq": 2, "u4": 0, "u5": 0, "u6": 0, "u7": 0, "u8": 0, "u9": 0, "u10": 0, "u11": 0 },
{ "teamSkillConditionId": "30020000", "teamSkillId": 19964003, "teamSkillMinPairsReq": 2, "u4": 40, "u5": 41, "u6": 0, "u7": 0, "u8": 0, "u9": 0, "u10": 0, "u11": 0 },
{ "teamSkillConditionId": "30020000", "teamSkillId": 19965001, "teamSkillMinPairsReq": 2, "u4": 40, "u5": 41, "u6": 0, "u7": 0, "u8": 0, "u9": 0, "u10": 0, "u11": 0 },
{ "teamSkillConditionId": "30020000", "teamSkillId": 19965002, "teamSkillMinPairsReq": 2, "u4": 0, "u5": 0, "u6": 0, "u7": 0, "u8": 0, "u9": 0, "u10": 0, "u11": 0 },
{ "teamSkillConditionId": "30020000", "teamSkillId": 19965003, "teamSkillMinPairsReq": 2, "u4": 40, "u5": 41, "u6": 0, "u7": 0, "u8": 0, "u9": 0, "u10": 0, "u11": 0 },
{ "teamSkillConditionId": "30020000", "teamSkillId": 19966002, "teamSkillMinPairsReq": 2, "u4": 0, "u5": 0, "u6": 0, "u7": 0, "u8": 0, "u9": 0, "u10": 0, "u11": 0 },
{ "teamSkillConditionId": "30020000", "teamSkillId": 19967001, "teamSkillMinPairsReq": 2, "u4": 40, "u5": 41, "u6": 0, "u7": 0, "u8": 0, "u9": 0, "u10": 0, "u11": 0 },
{ "teamSkillConditionId": "30020000", "teamSkillId": 19967003, "teamSkillMinPairsReq": 2, "u4": 40, "u5": 41, "u6": 0, "u7": 0, "u8": 0, "u9": 0, "u10": 0, "u11": 0 },
{ "teamSkillConditionId": "30020000", "teamSkillId": 19968001, "teamSkillMinPairsReq": 2, "u4": 40, "u5": 41, "u6": 0, "u7": 0, "u8": 0, "u9": 0, "u10": 0, "u11": 0 },
{ "teamSkillConditionId": "30020000", "teamSkillId": 19968002, "teamSkillMinPairsReq": 2, "u4": 0, "u5": 0, "u6": 0, "u7": 0, "u8": 0, "u9": 0, "u10": 0, "u11": 0 },
{ "teamSkillConditionId": "30020000", "teamSkillId": 19968003, "teamSkillMinPairsReq": 2, "u4": 40, "u5": 41, "u6": 0, "u7": 0, "u8": 0, "u9": 0, "u10": 0, "u11": 0 },
{ "teamSkillConditionId": "30020000", "teamSkillId": 19969001, "teamSkillMinPairsReq": 2, "u4": 40, "u5": 41, "u6": 0, "u7": 0, "u8": 0, "u9": 0, "u10": 0, "u11": 0 },
{ "teamSkillConditionId": "30020000", "teamSkillId": 19969002, "teamSkillMinPairsReq": 2, "u4": 0, "u5": 0, "u6": 0, "u7": 0, "u8": 0, "u9": 0, "u10": 0, "u11": 0 },
{ "teamSkillConditionId": "30020000", "teamSkillId": 19970001, "teamSkillMinPairsReq": 2, "u4": 40, "u5": 41, "u6": 0, "u7": 0, "u8": 0, "u9": 0, "u10": 0, "u11": 0 },
{ "teamSkillConditionId": "30020000", "teamSkillId": 19970002, "teamSkillMinPairsReq": 2, "u4": 0, "u5": 0, "u6": 0, "u7": 0, "u8": 0, "u9": 0, "u10": 0, "u11": 0 },
{ "teamSkillConditionId": "30020000", "teamSkillId": 19970003, "teamSkillMinPairsReq": 2, "u4": 40, "u5": 41, "u6": 0, "u7": 0, "u8": 0, "u9": 0, "u10": 0, "u11": 0 },
{ "teamSkillConditionId": "30020000", "teamSkillId": 19980001, "teamSkillMinPairsReq": 2, "u4": 40, "u5": 41, "u6": 0, "u7": 0, "u8": 0, "u9": 0, "u10": 0, "u11": 0 },
{ "teamSkillConditionId": "30020000", "teamSkillId": 19980002, "teamSkillMinPairsReq": 2, "u4": 0, "u5": 0, "u6": 0, "u7": 0, "u8": 0, "u9": 0, "u10": 0, "u11": 0 }
]}
