{
    "ch0017_00_leaf/0101_0701_01_10": "Eccoti qua, [Name:PlayerNickname ]!\nCome sta il tuo Pokémon?",
    "ch0017_00_leaf/0101_0701_02_10": "Mi raccomando, trattalo con tanto amore\ne non farlo stancare troppo!",
    "ch0017_00_leaf/0601_0701_01_10": "Proteggere i Pokémon è la mia regola\nnumero uno!",
    "ch0017_00_leaf/0601_0701_02_10": "Non per niente il mio Pokémon ha riconosciuto me\ncome sua Allenatrice! Me e nessun altro!",
    "ch0017_00_leaf/0601_0701_03_10": "Non permetterò a nessuno di far male a creaturine\ncosì dolci e uniche!",
    "ch0017_00_leaf/0601_0702_01_10": "Preferisco ferirmi io stessa piuttosto che vedere\nqualcuno a cui tengo farsi male!",
    "ch0017_00_leaf/0601_0702_02_10": "Sono certa che tu possa capirmi.",
    "ch0017_00_leaf/0602_0701_01_10": "A Pasio si lasciano spesso i Pokémon fuori\ndalla Poké Ball, no?",
    "ch0017_00_leaf/0602_0701_02_10": "Mi fa piacere avere il mio sempre accanto,\nperò sono anche preoccupata...",
    "ch0017_00_leaf/0602_0701_03_10": "E se qualcuno trovasse il mio Pokémon così carino\nda portarselo via?!",
    "ch0017_00_leaf/0602_0702_01_10": "Metti che chiedano al mio Pokémon di fare\nda modello perché è troppo grazioso...\nVuol dire che non potremmo più essere insieme?!",
    "ch0017_00_leaf/0602_0702_02_10": "N-No! Deve tornare subito nella Poké Ball!",
    "ch0017_00_leaf/0603_0701_01_10": "Ci sono tante cose di Pasio che trovo\naffascinanti... I profumi, per esempio!",
    "ch0017_00_leaf/0603_0701_02_10": "Adoro il profumo dei fiori che arriva dal bosco,\ntrasportato dal vento...",
    "ch0017_00_leaf/0603_0701_03_10": "Quando lo sento arrivare mi fermo all'improvviso,\ncome incantata...",
    "ch0017_00_leaf/0603_0701_04_10": "Però a volte la gente mi guarda in modo strano!",
    "ch0017_00_leaf/0603_0702_01_10": "Dalla città arriva il profumo dei manicaretti...\nDalla costa il profumo del mare...",
    "ch0017_00_leaf/0603_0702_02_10": "Non ci si stanca mai di un posto come Pasio!",
    "ch0017_00_leaf/0604_0701_01_10": "Attorno a Biancavilla, a Kanto, vivono un sacco\ndi Rattata.",
    "ch0017_00_leaf/0604_0701_02_10": "Una volta uno si è infilato di nascosto\nnella cucina di casa mia!",
    "ch0017_00_leaf/0604_0701_03_10": "Si è mangiucchiato tutto quello che avevo\npreparato per pranzo... Quando l'ho visto\nnon ci potevo credere!",
    "ch0017_00_leaf/0604_0701_04_10": "Però non ce l'ho fatta a prendermela con lui.\nMangiava così di gusto!",
    "ch0017_00_leaf/0604_0702_01_10": "I Pokémon ci riservano sempre delle sorprese,\nanche se viaggiano al nostro fianco da sempre.",
    "ch0017_00_leaf/0604_0702_02_10": "Per questo voglio sapere tutto su di loro!",
    "ch0017_00_leaf/0604_0702_03_10": "Dev'essere nella natura di ogni Allenatore, no?",
    "ch0017_00_leaf/0605_0701_01_10": "Ehi! Mi sono accorta di una cosa!",
    "ch0017_00_leaf/0605_0701_02_10": "Il mio Eevee è di una dolcezza imbattibile!",
    "ch0017_00_leaf/0605_0701_03_10": "Ma anche in quanto a potenza è imbattibile!",
    "ch0017_00_leaf/0605_0701_04_10": "Perciò... la nostra Unità è imbattibile in tutto\ne per tutto! Giusto?",
    "ch0017_00_leaf/0605_0702_01_10": "Potresti diventare [IT:Gen Ref=\"255\" M=\"il\" F=\"la\" ] mi[IT:Gen Ref=\"255\" M=\"o\" F=\"a\" ] rivale,\n[Name:PlayerNickname ]...",
    "ch0017_00_leaf/0605_0702_02_10": "Ti prendi molta cura del tuo Pokémon\ne hai un grande intuito nelle lotte...",
    "ch0017_00_leaf/1701_0701_01_10": "Ah, ecco dove ti eri cacciat[IT:Gen Ref=\"255\" M=\"o\" F=\"a\" ]!",
    "ch0017_00_leaf/1701_0701_02_10": "Volevo darti una cosa! Penso ti possa servire.",
    "ch0017_00_leaf/1701_0702_01_10": "Fai buon uso di ciò che ti ho dato, eh!",
    "ch0017_00_leaf/2501_0701_01_10": "Eevee ha delle zampette così morbide e soffici\nche potrei accarezzarle tutto il giorno!",
    "ch0017_00_leaf/2501_0701_02_10": "Ma anche se è piccolo e carino ha una potenza\nspaventosa, sai?",
    "ch0017_00_leaf/2501_0701_03_10": "So che posso contare su di lui, eppure...\nPer qualche motivo mi sembra indifeso e bisognoso\ndi protezione, non posso farci niente!",
    "ch0017_00_leaf/2501_0702_01_10": "I Pokémon hanno un fascino misterioso...",
    "ch0017_00_leaf/2501_0702_02_10": "Aaah... Li adoro, non c'è niente da fare!",
    "ch0017_00_leaf/2511_0701_01_10": "La mia ultima ossessione è fare corone di fiori\nper Eevee.",
    "ch0017_00_leaf/2511_0701_02_10": "Ci metto dei fiori che penso gli stiano bene\ne, quando gliele appoggio in testa, a volte fa\ndei versi di gioia, ma altre volte non reagisce.",
    "ch0017_00_leaf/2511_0701_03_10": "Evidentemente ha i suoi gusti!\nLa prossima volta devo provare con qualcos'altro!",
    "ch0017_00_leaf/2511_0702_01_10": "Quali saranno i fiori preferiti di Eevee?",
    "ch0017_00_leaf/2511_0702_02_10": "La prossima volta che faccio una corona di fiori\npotrei far scegliere a lui quali usare!",
    "ch0017_00_leaf/2511_0702_03_10": "Uh uh uh... Non vedo l'ora!",
    "ch0017_00_leaf/3001_0701_01_10": "Ora solleviamo le mani e usiamo Sintesi...\nAh no, gli Allenatori non sono capaci!",
    "ch0017_00_leaf/3002_0701_01_10": "Ehilà!\nSono fresca e pimpante fin dal mattino!",
    "ch0017_00_leaf/3003_0701_01_10": "Che bello essere qui a Pasio!\nCi sono così tante Unità da conoscere!",
    "ch0017_00_leaf/3004_0701_01_10": "Pasio ha solo paesaggi stupendi!\nSarebbe un peccato non girarla tutta!",
    "ch0017_00_leaf/3005_0701_01_10": "Di notte tutto ha un aspetto diverso...\nAllenatori, Pokémon, persino Pasio stessa!",
    "ch0017_00_leaf/3006_0701_01_10": "La notte non mi dispiace. Sai perché?\nPerché appaiono Pokémon che di giorno\nnon si vedono!"
}
