{
    "ch0250_00_saida/0101_0701_01_10": "[Name:PlayerNickname ]님\n기다리고 있었습니다",
    "ch0250_00_saida/0101_0701_02_10": "자, 오늘도\n한 수 부탁드립니다",
    "ch0250_00_saida/7101_0701_01_10": "역시 파시오...\n실력 좋은 버디즈뿐이군요",
    "ch0250_00_saida/7101_0701_02_10": "저도 질 수는 없죠",
    "ch0250_00_saida/7101_0701_03_10": "다른 분들께 지지 않도록\n오늘도 열심히 단련해야겠습니다!",
    "ch0250_00_saida/7102_0701_01_10": "산, 바다, 숲, 암석 지대... \n파시오에는 여러 종류의 지형이 있군요",
    "ch0250_00_saida/7102_0701_02_10": "단련하기에 정말 최적의 장소입니다",
    "ch0250_00_saida/7102_0701_03_10": "혹시 그것도 고려해서\n이 섬이 만들어진 거라면...",
    "ch0250_00_saida/7102_0701_04_10": "격투가로서 참으로 감사한 마음과\n존경심이 드네요",
    "ch0250_00_saida/7103_0701_01_10": "단련과 식사는\n아주 중요한 관계를 갖고 있습니다",
    "ch0250_00_saida/7103_0701_02_10": "단련한 뒤에는\n빨리 음식을 섭취해\n몸을 쉬게 해줘야 하죠!",
    "ch0250_00_saida/7103_0701_03_10": "음식 섭취 방법 한 가지를 바꾼 것만으로도\n보다 효율적으로 강해질 수 있습니다",
    "ch0250_00_saida/7104_0701_01_10": "부모님의 엄격한 가르침 덕분에\n저는 여기까지 강해질 수 있었습니다",
    "ch0250_00_saida/7104_0701_02_10": "가라르태권도의 이름을\n전 세계에 알리는 것",
    "ch0250_00_saida/7104_0701_03_10": "그것이 부모님께서\n베풀어 주신 은혜에 보답하는\n최고의 방법이겠지요",
    "ch0250_00_saida/7105_0701_01_10": "우물우물...",
    "ch0250_00_saida/7105_0701_02_10": "앗, [Name:PlayerNickname ]님!?\n언제부터 거기 계셨던 거죠!?",
    "ch0250_00_saida/7105_0701_03_10": "의, 의외인가요?\n이래 봬도 저는 달콤한 걸 좋아해요",
    "ch0250_00_saida/7105_0701_04_10": "다른 사람들에게는\n절대 말하지 말아 주세요\n부끄러우니까요...",
    "ch0250_00_saida/1701_0701_01_10": "이걸 받아주세요",
    "ch0250_00_saida/1701_0701_02_10": "버디와 단련하는 데\n분명 도움이 될 겁니다",
    "ch0250_00_saida/1701_0702_01_10": "아까 건네드린 도구\n한번 사용해보세요",
    "ch0250_00_saida/2501_0701_01_10": "저는 다가가기 힘든 사람인가요?",
    "ch0250_00_saida/2501_0701_02_10": "가끔 생각을 읽지 못하겠다는\n말을 들을 때가 있습니다",
    "ch0250_00_saida/2501_0701_03_10": "저는 그저\n상대에게 빈틈을 보이지 않기 위해\n긴장하고 있는 것뿐입니다만...",
    "ch0250_00_saida/2501_0702_01_10": "...약한 모습을 보여버렸네요",
    "ch0250_00_saida/2501_0702_02_10": "마음이 흐트러져 있다는 증거겠지요\n마음의 유약함은 자기 자신의 유약함입니다",
    "ch0250_00_saida/2501_0702_03_10": "더욱 정신을 단련하기 위해\n트레이닝하고 오겠습니다!",
    "ch0250_00_saida/2511_0701_01_10": "저는 디저트를 좋아합니다만\n다른 사람들에게는 비밀로 하고 있어요",
    "ch0250_00_saida/2511_0701_02_10": "하지만 어째선지\n팬분들이 그걸 아셔서...",
    "ch0250_00_saida/2511_0701_03_10": "가게에서 몰래\n디저트를 즐기기 어려워졌어요...",
    "ch0250_00_saida/2511_0702_01_10": "파시오에는\n어떤 디저트 가게가 있는지 아시나요?",
    "ch0250_00_saida/2511_0702_02_10": "괜찮다면\n다음에 살짝 가르쳐주세요",
    "ch0250_00_saida/2511_0702_03_10": "...아시겠지요?\n아무쪼록 살짝 가르쳐주셔야 합니다",
    "ch0250_00_saida/3001_0701_01_10": "좋은 아침입니다\n지금부터 가볍게 10km 정도\n뛰러 가지 않으시겠어요?",
    "ch0250_00_saida/3003_0701_01_10": "안녕하세요\n힘들 땐 당분 섭취를 추천해드립니다\n예를 들면 아이스크림이라던가요...",
    "ch0250_00_saida/3005_0701_01_10": "밤에는 버디와 이야기를 나눕니다\n말이 통하지 않아도\n마음은 느낄 수 있으니까요"
}
