{
    "search_01_003/4301_1001_0100_10": "¡Maravilloso! ¡Extraordinario!\nParece que ya eres tod[ES:Gen Ref=\"255\" M=\"o\" F=\"a\" ] un[ES:Gen Ref=\"255\" F=\"a\" ] expert[ES:Gen Ref=\"255\" M=\"o\" F=\"a\" ] en los\ncombates Pokémon de Passio.",
    "search_01_003/4301_1001_0200_10": "Ver combates tan de cerca me viene de perlas\npara mi investigación.",
    "search_01_003/4301_1001_0300_10": "Es importante que todos los compis que vienen\na Passio sean capaces de utilizar movimientos\ncompi.",
    "search_01_003/4301_1001_0400_10": "Por eso todos los que llegan aquí reciben un\nPorygófono con una Piedra Compi dentro.",
    "search_01_003/4301_1001_0500_10": "No olvides que, cuanto más fuerte sea el vínculo\nque te une a tu Pokémon, más fuerte se volverá\nvuestro Poder Compi.",
    "search_01_003/4301_1001_0600_10": "Bueno, tengo que seguir con mis cosas.\nEspero que mis investigaciones sean fructíferas\ny ayuden a todo el mundo.",
    "search_01_003/4301_1001_0700_10": "¡Doy por concluido el trabajo de campo de hoy!\nMuchas gracias, [Name:PlayerNickname ].\n¡Hasta pronto!"
}
