{
    "search_03_002/4301_0101_0100_10": "Estos impresentables del Team Break no hacen\nmás que entorpecer el torneo que el jefe tanto\nse ha esforzado en organizar.",
    "search_03_002/4301_0101_0200_10": "Creo que todavía no hemos acabado con todos.\nEs más, ahí hay unos cuantos.",
    "search_03_002/4301_0101_0300_10": "¿Pero tú de qué vas con esas pintas tan raras?\nPor no hablar de la tipa esa que te acompaña.\n¡Dais pena! ¡Fuera de aquí!",
    "search_03_002/4301_0101_0400_10": "¡No sabes con quién te estás metiendo! El gran\nAlik nos ha enviado para mantener la paz en el\nWPM. No toleraré que nos hables de esa manera.",
    "search_03_002/4301_0101_0500_10": "¡Vosotros, encargaos de esos dos pringaos!\nDe est[ES:Gen Ref=\"255\" M=\"e\" F=\"a\" ] de aquí me encargo yo.",
    "search_03_002/4301_0501_0100_10": "No pensé que esto acabaría así...\n¡No nos queda otra que salir por patas!",
    "search_03_002/4301_0501_0200_10": "Bueno, pues ya está. Tenemos que ir a informar\nal jefe.",
    "search_03_002/4301_0501_0300_10": "No, creo que deberíamos hacer otra ronda.\nPassio está llena de miembros del Team Break\ny tenemos que encontrarlos a todos.",
    "search_03_002/4301_0501_0400_10": "¿Has oído, [Name:PlayerNickname ]?\nVamos a necesitar tu ayuda un rato más."
}
