{
    "story_01_01000/2401_1001_0100_10": "¡Nos encontramos en Centrópolis, la ciudad más\ngrande de toda la isla artificial de Passio!",
    "story_01_01000/2401_1001_0200_10": "Creo que me sé de alguien más que estaría\nencantada de unirse a tu equipo. ¿Por qué no\nvamos a buscarla?",
    "story_01_01000/2401_1001_0300_10": "Ah, ¿te refieres a aquella chica de Teselia?\nCreo que podremos encontrarla en la plaza que\nhay más adelante.",
    "story_01_01000/2401_1001_0400_10": "¡Parad, por favor! ¡No podéis forzar a la gente\na combatir cuando no quiere! ¡Eso va en contra\nde las normas!",
    "story_01_01000/2401_1001_0500_10": "¿Eh? ¿Y este escándalo?",
    "story_01_01000/2401_1001_0600_10": "Parece que están discutiendo por algo. Será\nmejor que vayamos a echar un vistazo y nos\naseguremos de que no hay nadie en apuros.",
    "story_01_01000/2401_1001_0700_10": "Lo lamento, pero mis Pokémon no se encuentran\nahora mismo en condiciones de combatir. No\nquiero forzarlos.",
    "story_01_01000/2401_1001_0800_10": "¡Ya lo habéis oído! Si de verdad queréis\ncombatir contra ella, será mejor que volváis\nen otro momento.",
    "story_01_01000/2401_1001_0900_10": "¿En otro momento? ¡No tenemos otro momento!\nQueremos combatir contra la Campeona Cintia,\n¡aquí y ahora!",
    "story_01_01000/2401_1001_1000_10": "Una oportunidad como esta solo se presenta una\nvez cada mil años. ¡De aquí no nos vamos sin\nhaber combatido!",
    "story_01_01000/2401_1001_1100_10": "¡Eh, vosotros! Dejad de insistir, ¿o es que no\nveis que las estáis incomodando?",
    "story_01_01000/2401_1001_1200_10": "¿Brock? ¿Misty?",
    "story_01_01000/2401_1001_1300_10": "¡Hala, Nanci! Parece que os habéis metido en un\nbuen aprieto, ¿no? No os preocupéis, nosotros\nnos encargamos de esto.",
    "story_01_01000/2401_1001_1400_10": "¿De dónde habéis salido vosotros? ¿Y nos estáis\ndesafiando a un combate? ¡Muy bien! Si lo que\nqueréis es una tunda, las repartimos gratis."
}
